{
  "user": [
    {
      "id": "07FG",
      "name": "Fabian Guerrero",
      "balance": 150000,
      "active_subscriptions": [
        {
          "fund_id": "5",
          "fund_name": "FPV_BTG_PACTUAL_DINAMICA",
          "amount": 100000,
          "subscribed_at": "2026-03-21T12:09:19.504"
        },
        {
          "fund_id": "3",
          "fund_name": "DEUDAPRIVADA",
          "amount": 50000,
          "subscribed_at": "2026-03-21T12:09:22.454"
        },
        {
          "fund_id": "1",
          "fund_name": "FPV_BTG_PACTUAL_RECAUDADORA",
          "amount": 75000,
          "subscribed_at": "2026-03-21T12:09:51.586"
        },
        {
          "fund_id": "2",
          "fund_name": "FPV_BTG_PACTUAL_ECOPETROL",
          "amount": 125000,
          "subscribed_at": "2026-03-21T12:10:43.152"
        }
      ]
    }
  ],
  "funds": [
    {
      "id": "1",
      "name": "FPV_BTG_PACTUAL_RECAUDADORA",
      "minimum_amount": 75000,
      "category": "FPV"
    },
    {
      "id": "2",
      "name": "FPV_BTG_PACTUAL_ECOPETROL",
      "minimum_amount": 125000,
      "category": "FPV"
    },
    {
      "id": "3",
      "name": "DEUDAPRIVADA",
      "minimum_amount": 50000,
      "category": "FIC"
    },
    {
      "id": "4",
      "name": "FDO-ACCIONES",
      "minimum_amount": 250000,
      "category": "FIC"
    },
    {
      "id": "5",
      "name": "FPV_BTG_PACTUAL_DINAMICA",
      "minimum_amount": 100000,
      "category": "FPV"
    }
  ],
  "transactions": [
    {
      "id": "d84554ea-a647-4263-bc84-b399502a1fc8",
      "fund_id": "4",
      "fund_name": "FDO-ACCIONES",
      "amount": 250000,
      "type": "subscription",
      "notification_method": "sms",
      "created_at": "2026-03-21T12:08:51.166"
    },
    {
      "id": "3697c093-e8f8-431c-96a8-c02779442021",
      "fund_id": "5",
      "fund_name": "FPV_BTG_PACTUAL_DINAMICA",
      "amount": 100000,
      "type": "subscription",
      "notification_method": "email",
      "created_at": "2026-03-21T12:09:19.601"
    },
    {
      "id": "ca135b47-21f5-4234-b91c-709cbf7467b7",
      "fund_id": "3",
      "fund_name": "DEUDAPRIVADA",
      "amount": 50000,
      "type": "subscription",
      "notification_method": "sms",
      "created_at": "2026-03-21T12:09:22.567"
    },
    {
      "id": "c7e8b527-2d84-499a-9728-ab3a58d24c22",
      "fund_id": "1",
      "fund_name": "FPV_BTG_PACTUAL_RECAUDADORA",
      "amount": 75000,
      "type": "subscription",
      "notification_method": "sms",
      "created_at": "2026-03-21T12:09:51.670"
    },
    {
      "id": "3b252400-7739-497f-a33c-8b3eb95e4d86",
      "fund_id": "4",
      "fund_name": "FDO-ACCIONES",
      "amount": 250000,
      "type": "cancellation",
      "notification_method": "sms",
      "created_at": "2026-03-21T12:09:59.250"
    },
    {
      "id": "10f3c26a-7325-4366-99ea-1518b007724e",
      "fund_id": "2",
      "fund_name": "FPV_BTG_PACTUAL_ECOPETROL",
      "amount": 125000,
      "type": "subscription",
      "notification_method": "sms",
      "created_at": "2026-03-21T12:10:43.219"
    }
  ]
}